README.rst
setup.py
jw.lognotify.egg-info/PKG-INFO
jw.lognotify.egg-info/SOURCES.txt
jw.lognotify.egg-info/dependency_links.txt
jw.lognotify.egg-info/entry_points.txt
jw.lognotify.egg-info/requires.txt
jw.lognotify.egg-info/top_level.txt
main/__init__.py
main/main.py