Metadata-Version: 1.1
Name: jw.lognotify
Version: 0.3
Summary: Notify about logfile events in real-time
Home-page: https://pypi.python.org/pypi/jw.lognotify
Author: Johnny Wezel
Author-email: dev-jay@wezel.name
License: GPL
Keywords: logfile notifications
Platform: Posix
Classifier: Development Status :: 4 - Beta
Classifier: Environment :: Console
Classifier: Intended Audience :: Information Technology
Classifier: License :: OSI Approved :: GNU General Public License v3 or later (GPLv3+)
Classifier: Natural Language :: English
Classifier: Operating System :: POSIX
Classifier: Operating System :: Unix
Classifier: Programming Language :: Python :: 2.7
Classifier: Programming Language :: Python :: 3
Classifier: Topic :: System :: Monitoring
